__init__.py
ai_execute-0.1.1.dist-info/licenses/LICENSE
aix/__init__.py
aix/cli.py
aix/cmd.py
aix/prompt.py
ai_execute-0.1.1.dist-info/METADATA
ai_execute-0.1.1.dist-info/WHEEL
ai_execute-0.1.1.dist-info/entry_points.txt
ai_execute-0.1.1.dist-info/top_level.txt
ai_execute-0.1.1.dist-info/RECORD
