Metadata-Version: 2.4
Name: ai-execute
Version: 0.1.1
Summary: Use AI to generate terminal commands
Author: AlexanderJCS
Project-URL: repository, https://github.com/AlexanderJCS/aix
Project-URL: homepage, https://github.com/AlexanderJCS/aix
Project-URL: issues, https://github.com/AlexanderJCS/aix/issues
Classifier: Programming Language :: Python :: 3
Classifier: License :: OSI Approved :: MIT License
Classifier: Operating System :: OS Independent
Requires-Python: >=3.9
License-File: LICENSE
Requires-Dist: colorama~=0.4.6
Requires-Dist: ollama~=0.4.8
Dynamic: license-file
